graphguest/__init__.py
graphguest/evaluate_module.py
graphguest/guest.py
graphguest/helper_module.py
graphguest/interactions_module.py
graphguest/optimizer_module.py
graphguest/reorder_module.py
graphguest/rmsd_module.py
graphguest/splits_module.py
graphguest-1.1.0.dist-info/LICENSE
graphguest-1.1.0.dist-info/METADATA
graphguest-1.1.0.dist-info/WHEEL
graphguest-1.1.0.dist-info/top_level.txt
graphguest-1.1.0.dist-info/RECORD
