Metadata-Version: 2.1
Name: graphguest
Version: 1.1.0
Summary: Graph Universal Embedding Splitting Tool
Author-email: Jesús de la Fuente Cedeño <jdlfuentec@gmail.com>
License: MIT License
Project-URL: Homepage, https://github.com/ubioinformat/guest
Keywords: graph embedding,pypi,drug repurposing,splitting,graph embedding splitting
Classifier: License :: OSI Approved :: MIT License
Classifier: Programming Language :: Python
Classifier: Programming Language :: Python :: 3
Classifier: Programming Language :: Python :: 3.6
Classifier: Programming Language :: Python :: 3.7
Classifier: Programming Language :: Python :: 3.8
Classifier: Programming Language :: Python :: 3.9
Classifier: Programming Language :: Python :: 3 :: Only
Classifier: Operating System :: OS Independent
Requires-Python: >=3
License-File: LICENSE
Requires-Dist: pandas
Requires-Dist: scikit-learn
Requires-Dist: tqdm
Provides-Extra: dev
Requires-Dist: black ; extra == 'dev'
Requires-Dist: bumpver ; extra == 'dev'
Requires-Dist: isort ; extra == 'dev'
Requires-Dist: pip-tools ; extra == 'dev'
Requires-Dist: pytest ; extra == 'dev'
